gscpy/GSC.py
gscpy/__init__.py
gscpy/dataset_builder.py
gscpy/utils/__init__.py
gscpy/utils/error_handling.py
gscpy/utils/file_manager.py
gscpy/utils/graphs.py
gscpy/utils/labels_ordering.py
gscpy/utils/spectral_clustering.py
GSCpy-1.0.2.dist-info/METADATA
GSCpy-1.0.2.dist-info/WHEEL
GSCpy-1.0.2.dist-info/top_level.txt
GSCpy-1.0.2.dist-info/RECORD
