Metadata-Version: 2.1
Name: GSCpy
Version: 1.0.2
Summary: Generalized Spectral Clustering in Python
Home-page: https://github.com/Malik-Hacini/GSCpy
Author: Malik Hacini
Author-email: mhacini.pro@gmail.com
Classifier: Programming Language :: Python :: 3
Classifier: License :: OSI Approved :: MIT License
Classifier: Operating System :: OS Independent
Requires-Python: >=3.6
Requires-Dist: numpy
Requires-Dist: matplotlib
Requires-Dist: scipy
Requires-Dist: scikit-learn
